heroku3/__init__.py
heroku3/api.py
heroku3/core.py
heroku3/exceptions.py
heroku3/helpers.py
heroku3/rendezvous.py
heroku3/structures.py
heroku3/data/cacert.pem
heroku3/models/__init__.py
heroku3/models/addon.py
heroku3/models/app.py
heroku3/models/app_setup.py
heroku3/models/build.py
heroku3/models/buildpack.py
heroku3/models/buildpack_installation.py
heroku3/models/collaborator.py
heroku3/models/configvars.py
heroku3/models/domain.py
heroku3/models/dyno.py
heroku3/models/formation.py
heroku3/models/invoice.py
heroku3/models/key.py
heroku3/models/logdrain.py
heroku3/models/logsession.py
heroku3/models/oauth.py
heroku3/models/region.py
heroku3/models/release.py
heroku3/models/slug.py
heroku3/models/sni_endpoint.py
heroku3/models/sourceblob.py
heroku3/models/ssl_cert.py
heroku3/models/account/__init__.py
heroku3/models/account/feature.py
herokum-5.1.8.dist-info/AUTHORS.rst
herokum-5.1.8.dist-info/LICENSE
herokum-5.1.8.dist-info/METADATA
herokum-5.1.8.dist-info/WHEEL
herokum-5.1.8.dist-info/top_level.txt
herokum-5.1.8.dist-info/RECORD
