Metadata-Version: 2.1
Name: herokum
Version: 5.1.8
Summary: Heroku API Wrapper.
Home-page: https://github.com/MUTLCC/herokum
Download-URL: https://github.com/MUTLCC/herokum/
Author: Mutlu
Author-email: 
License: MIT
Platform: UNKNOWN
Classifier: Development Status :: 5 - Production/Stable
Classifier: Intended Audience :: Developers
Classifier: Natural Language :: English
Classifier: License :: OSI Approved :: MIT License
Classifier: Programming Language :: Python
Classifier: Programming Language :: Python :: 2.7
Classifier: Programming Language :: Python :: 3.4
Classifier: Programming Language :: Python :: 3.5
Classifier: Programming Language :: Python :: 3.6
License-File: LICENSE
License-File: AUTHORS.rst
Requires-Dist: requests (>=1.2.3)
Requires-Dist: python-dateutil (>=2.6.0)
